[{"index":0,"Itinerary":[[1.2931,103.852],"Merlion Park","Little India","Fifth Season's Tangra Chinese","Fifth Season's Kolkata Beckons"],"POICategories":[["NA","NA","NA"],["nonfood","Parks","City Parks"],["nonfood","Places of Interest","Lifestyle"],["food","NA","NA"],["food","NA","NA"]],"VehicleMode":"Cycle","Coords":[[1.2931,103.852],[1.2861885928,103.85415714],[1.3067017019,103.8517943356],[1.3077992153,103.8506522113],[1.3082766366,103.8510258281]],"StartTimePOI":[["Fri, 22 Sep 2023 10:00:00 GMT"],["Fri, 22 Sep 2023 11:07:42 GMT"],["Fri, 22 Sep 2023 12:25:34 GMT"],["Fri, 22 Sep 2023 13:28:37 GMT"]],"ReachTimePOI":[["Fri, 22 Sep 2023 10:07:42 GMT"],["Fri, 22 Sep 2023 11:25:34 GMT"],["Fri, 22 Sep 2023 12:28:37 GMT"],["Fri, 22 Sep 2023 13:29:02 GMT"]],"LeaveTimePOI":[["Fri, 22 Sep 2023 11:07:42 GMT"],["Fri, 22 Sep 2023 12:25:34 GMT"],["Fri, 22 Sep 2023 13:28:37 GMT"],["Fri, 22 Sep 2023 14:29:02 GMT"]],"TotalTime":"4h 29min","Total distance(km)":4.347,"Routes":[{"route_geometry":"qq{FypzxRh@VzAx@TJx@`@dAj@tExBFB`B~@lAaBd@m@V]r@{@Be@GU[Ut@@ZINIPS`@o@Ns@HY@IDGHAJ?PDRBR@r@GPM~ByCfAk@~AaAC?","route_instructions":[["Left","NORTH BRIDGE ROAD",393,"1.293213,103.851814",149,"393m","South West","North","cycling","Head Southwest On North Bridge Road"],["Left","PARLIAMENT PLACE",223,"1.290185,103.849996",92,"223m","South East","South West","cycling","Turn Left Onto Parliament Place"],["Sharp Right","CONNAUGHT DRIVE",57,"1.289392,103.851578",52,"57m","South","North East","pushing bike","Make A Sharp Right Onto Connaught Drive"],["Straight","CONNAUGHT DRIVE",48,"1.288903,103.851673",18,"48m","South East","South East","cycling","Continue Straight Onto Connaught Drive"],["Straight","CONNAUGHT DRIVE",103,"1.288639,103.852012",38,"103m","East","South East","cycling","Continue Straight To Stay On Connaught Drive"],["Straight","FULLERTON ROAD",264,"1.288066,103.852437",113,"264m","South","South","cycling","Go Straight Onto Fullerton Road"],["Sharp Left","ESPLANADE DRIVE",2,"1.286244,103.853866",2,"2m","North","South East","pushing bike","Make A Sharp Left Onto Esplanade Drive"],["Right","ESPLANADE DRIVE",0,"1.28626,103.85387",0,"0m","North","North","pushing bike","You Have Arrived At Your Destination, On The Right"]],"route_name":["NORTH BRIDGE ROAD","FULLERTON ROAD"],"route_summary":{"end_point":"ESPLANADE DRIVE","start_point":"NORTH BRIDGE ROAD","total_distance":1089,"total_time":462},"status":0,"status_message":"Found route between points"},{"alternativeroute":[{"route_geometry":"cfzFu}zxRq@K@RGLaPcBkEi@_Ca@gBi@EDg@l@{@p@uArAO@S?MEWIwAu@_@Oo@[}@i@]AsBkAqCyAmBgAyAy@YQw@e@YSk@a@y@q@_@]i@g@oBuBsB`BqD|CaD|CyC~C{CdCeBdAiAh@[b@Yb@a@n@_@~@Sx@Ux@c@dAWj@a@`Ak@|A]t@kAi@g@a@w@a@qAq@QKm@_@q@]OR","route_instructions":[["Right","ESPLANADE DRIVE",29,"1.28626,103.85387",39,"29m","North","North","pushing bike","Head North On Esplanade Drive"],["Left","ESPLANADE DRIVE",21,"1.286511,103.853932",11,"21m","West","North","cycling","Turn Left To Stay On Esplanade Drive"],["Right","ESPLANADE DRIVE",561,"1.286538,103.853759",207,"561m","North","North West","cycling","Turn Right To Stay On Esplanade Drive"],["Left","STAMFORD ROAD",149,"1.291448,103.854847",55,"149m","North West","North","cycling","Turn Left Onto Stamford Road"],["Right","BEACH ROAD",194,"1.292406,103.853918",71,"194m","North","North West","cycling","Turn Right Onto Beach Road"],["Slight Left","BEACH ROAD",616,"1.293934,103.854685",230,"616m","North","North East","cycling","Make A Slight Left To Stay On Beach Road"],["Left","ROCHOR ROAD",650,"1.298368,103.857923",234,"650m","North West","North East","cycling","Turn Left Onto Rochor Road"],["Slight Right","ROCHOR ROAD",48,"1.302709,103.854031",18,"48m","North West","North West","cycling","Keep Right Onto Rochor Road"],["Slight Left","ROCHOR CANAL ROAD",397,"1.303078,103.853816",147,"397m","North West","North West","cycling","Continue Slightly Left Onto Rochor Canal Road"],["Right","SERANGOON ROAD",243,"1.304734,103.850682",95,"243m","North East","North West","cycling","Turn Right Onto Serangoon Road"],["Left","KERBAU ROAD",15,"1.306566,103.851854",13,"15m","North West","North East","pushing bike","Turn Left Onto Kerbau Road"],["Right","KERBAU ROAD",0,"1.306646,103.851751",0,"0m","North","North West","pushing bike","You Have Arrived At Your Destination, On The Right"]],"route_name":["ESPLANADE DRIVE","BEACH ROAD"],"route_summary":{"end_point":"KERBAU ROAD","start_point":"ESPLANADE DRIVE","total_distance":2917,"total_time":1116},"status":0,"status_message":"Found route between points"}],"route_geometry":"cfzFu}zxRq@K@RGLaPcBkEi@_Ca@gBi@EDg@l@{@p@uArA}@~Ag@dAk@`Ag@~@a@r@K\\}AnC{AnC{@bB]~@_CmAQ?Q@KFSR]`@_@d@WR[T]P{@d@{@l@oBbCu@ESGsAgA{CiCo@WcIyA]Eo@CaAGqEAIAuAGq@G_@Ig@KWO[QiAq@kAi@g@a@w@a@qAq@QKm@_@q@]OR","route_instructions":[["Right","ESPLANADE DRIVE",29,"1.28626,103.85387",39,"29m","North","North","pushing bike","Head North On Esplanade Drive"],["Left","ESPLANADE DRIVE",21,"1.286511,103.853932",11,"21m","West","North","cycling","Turn Left To Stay On Esplanade Drive"],["Right","ESPLANADE DRIVE",561,"1.286538,103.853759",207,"561m","North","North West","cycling","Turn Right To Stay On Esplanade Drive"],["Left","STAMFORD ROAD",690,"1.291448,103.854847",254,"690m","North West","North","cycling","Turn Left Onto Stamford Road"],["Right","STAMFORD ROAD",83,"1.294948,103.849774",31,"83m","North East","North West","cycling","Turn Right To Stay On Stamford Road"],["Slight Left","STAMFORD ROAD",332,"1.295586,103.850156",121,"332m","North","North East","cycling","Keep Left Onto Stamford Road"],["Right","PRINSEP STREET",250,"1.297809,103.848271",91,"250m","North","North West","cycling","Turn Right Onto Prinsep Street"],["Straight","SELEGIE ROAD",593,"1.299621,103.849513",214,"593m","North","North East","cycling","Continue Onto Selegie Road"],["Straight","SERANGOON ROAD",243,"1.304734,103.850682",95,"243m","North East","North East","cycling","Continue Onto Serangoon Road"],["Left","KERBAU ROAD",15,"1.306566,103.851854",13,"15m","North West","North East","pushing bike","Turn Left Onto Kerbau Road"],["Right","KERBAU ROAD",0,"1.306646,103.851751",0,"0m","North","North West","pushing bike","You Have Arrived At Your Destination, On The Right"]],"route_name":["ESPLANADE DRIVE","STAMFORD ROAD"],"route_summary":{"end_point":"KERBAU ROAD","start_point":"ESPLANADE DRIVE","total_distance":2813,"total_time":1072},"status":0,"status_message":"Found route between points"},{"route_geometry":"qe~FmpzxRNSp@\\l@^{ApBqCvDQKkAu@_@W","route_instructions":[["Left","KERBAU ROAD",15,"1.306646,103.851751",9,"15m","South East","North","cycling","Head Southeast On Kerbau Road"],["Right","SERANGOON ROAD",64,"1.306566,103.851854",62,"64m","South West","South East","pushing bike","Turn Right Onto Serangoon Road"],["Right","BUFFALO ROAD",213,"1.306087,103.851541",81,"213m","North West","South West","cycling","Turn Right Onto Buffalo Road"],["Right","RACE COURSE ROAD",86,"1.307284,103.850048",31,"86m","North East","North West","cycling","Turn Right Onto Race Course Road"],["Right","RACE COURSE ROAD",0,"1.307912,103.850497",0,"0m","North","North East","cycling","You Have Arrived At Your Destination, On The Right"]],"route_name":["SERANGOON ROAD","BUFFALO ROAD"],"route_summary":{"end_point":"RACE COURSE ROAD","start_point":"KERBAU ROAD","total_distance":377,"total_time":183},"status":0,"status_message":"Found route between points"},{"route_geometry":"mm~FshzxR}AcACC","route_instructions":[["Right","RACE COURSE ROAD",68,"1.307912,103.850497",25,"68m","North East","North","cycling","Head Northeast On Race Course Road"],["Right","RACE COURSE ROAD",0,"1.308404,103.850858",0,"0m","North","North East","cycling","You Have Arrived At Your Destination, On The Right"]],"route_name":["RACE COURSE ROAD"],"route_summary":{"end_point":"RACE COURSE ROAD","start_point":"RACE COURSE ROAD","total_distance":68,"total_time":25},"status":0,"status_message":"Found route between points"}],"user_exist_in_db":true},{"index":1,"Itinerary":[[1.2931,103.852],"Armenian Apostolic Church of St. Gregory the Illuminator","Buddha Tooth Relic Temple","elemen \u5143\u7d20","Eighteen Chefs AMK Hub"],"POICategories":[["NA","NA","NA"],["nonfood","Place of Worship ","NA"],["nonfood","Place of Worship ","Temple"],["food","NA","NA"],["food","NA","NA"]],"VehicleMode":"Cycle","Coords":[[1.2931,103.852],[1.2930995692,103.8494005152],[1.2814943848,103.844241653],[1.2929650415,103.8593439689],[1.369193179,103.8484647756]],"StartTimePOI":[["Fri, 22 Sep 2023 10:00:00 GMT"],["Fri, 22 Sep 2023 11:02:36 GMT"],["Fri, 22 Sep 2023 12:12:21 GMT"],["Fri, 22 Sep 2023 13:32:07 GMT"]],"ReachTimePOI":[["Fri, 22 Sep 2023 10:02:36 GMT"],["Fri, 22 Sep 2023 11:12:21 GMT"],["Fri, 22 Sep 2023 12:32:07 GMT"],["Fri, 22 Sep 2023 14:55:34 GMT"]],"LeaveTimePOI":[["Fri, 22 Sep 2023 11:02:36 GMT"],["Fri, 22 Sep 2023 12:12:21 GMT"],["Fri, 22 Sep 2023 13:32:07 GMT"],["Fri, 22 Sep 2023 15:55:34 GMT"]],"TotalTime":"5h 55min","Total distance(km)":17.704,"Routes":[{"route_geometry":"qq{FypzxRh@VzAx@TJx@`@dAj@aAzBmAtCMEgA_@","route_instructions":[["Left","NORTH BRIDGE ROAD",186,"1.293213,103.851814",71,"186m","South West","North","cycling","Head Southwest On North Bridge Road"],["Right","COLEMAN STREET",173,"1.291789,103.850951",66,"173m","North West","South West","cycling","Turn Right Onto Coleman Street"],["Right","HILL STREET",53,"1.292506,103.849577",20,"53m","North","North West","cycling","Turn Right Onto Hill Street"],["Left","HILL STREET",0,"1.292943,103.849765",0,"0m","North","North East","cycling","You Have Arrived At Your Destination, On The Left"]],"route_name":["NORTH BRIDGE ROAD","COLEMAN STREET"],"route_summary":{"end_point":"HILL STREET","start_point":"NORTH BRIDGE ROAD","total_distance":411,"total_time":156},"status":0,"status_message":"Found route between points"},{"route_geometry":"{o{FadzxRfA^LD`ExATHjA`@jDyEpBhAd@VjB~@nAv@\\JRFRJVLxAr@lAj@vBdANDPJbErBrAt@NLhAf@HDjAj@bBz@rAp@`Af@`@RzAt@tAp@PJ`Ad@KLg@fA","route_instructions":[["Right","HILL STREET",232,"1.292943,103.849765",90,"232m","South West","North","cycling","Head Southwest On Hill Street"],["Left","HIGH STREET",155,"1.291052,103.848905",60,"155m","South East","South West","cycling","Turn Left Onto High Street"],["Right","NORTH BRIDGE ROAD",101,"1.290185,103.849996",37,"101m","South West","South East","cycling","Turn Right Onto North Bridge Road"],["Straight","SOUTH BRIDGE ROAD",367,"1.289426,103.849509",132,"367m","South West","South West","cycling","Continue Onto South Bridge Road"],["Slight Left","SOUTH BRIDGE ROAD",671,"1.286582,103.847854",247,"671m","South West","South West","cycling","Keep Left Onto South Bridge Road"],["Right","SAGO STREET",57,"1.281402,103.844772",21,"57m","North West","South West","cycling","Turn Right Onto Sago Street"],["Left","SAGO STREET",0,"1.281664,103.844335",0,"0m","North","North West","cycling","You Have Arrived At Your Destination, On The Left"]],"route_name":["HILL STREET","SOUTH BRIDGE ROAD"],"route_summary":{"end_point":"SAGO STREET","start_point":"HILL STREET","total_distance":1581,"total_time":585},"status":0,"status_message":"Found route between points"},{"alternativeroute":[{"route_geometry":"kiyFcbyxRc@`Ag@dAsAm@sAo@_Bu@}BtEuAeAe@c@KDGDAJBPu@o@UUqDqCwBaB}CcCc@]aA}@kA_A_Aq@m@g@oCsBkAy@[WIk@KGcAm@cBw@KGjDyElAaBd@m@V]r@{@Be@GU[UmBu@mEuBuGwCSUOa@Sw@[m@wAu@_@Oo@[}@i@r@w@j@eAt@cBP]r@kAx@aBZs@F[A[IQKMq@[C[aBw@NeFJ?@S","route_instructions":[["Left","SAGO STREET",87,"1.281664,103.844335",36,"87m","North West","North","cycling","Head Northwest On Sago Street"],["Right","TRENGGANU STREET",169,"1.282038,103.843655",69,"169m","North East","North West","cycling","Continue Right Onto Trengganu Street"],["Left","PAGODA STREET",139,"1.283357,103.844401",55,"139m","North West","North East","cycling","Turn Left Onto Pagoda Street"],["Right","NEW BRIDGE ROAD",91,"1.283991,103.84333",87,"91m","North East","North West","pushing bike","Turn Right Onto New Bridge Road"],["Left","EU TONG SEN STREET",30,"1.284614,103.843857",38,"30m","North West","North East","pushing bike","Turn Left Onto Eu Tong Sen Street"],["Sharp Right","EU TONG SEN STREET",798,"1.284703,103.843654",289,"798m","North East","West","cycling","Make A Sharp Right To Stay On Eu Tong Sen Street"],["Left","HILL STREET",126,"1.290094,103.848318",51,"126m","North East","East","cycling","Turn Left Onto Hill Street"],["Right","HIGH STREET",155,"1.291052,103.848905",56,"155m","South East","North East","cycling","Turn Right Onto High Street"],["Straight","PARLIAMENT PLACE",223,"1.290185,103.849996",82,"223m","South East","South East","cycling","Continue Onto Parliament Place"],["Straight","SAINT ANDREW'S ROAD",377,"1.289392,103.851578",136,"377m","North East","North East","cycling","Continue Onto Saint Andrew's Road"],["Slight Right","SAINT ANDREW'S ROAD",101,"1.292362,103.853201",37,"101m","North East","North East","cycling","Keep Right Onto Saint Andrew's Road"],["Slight Left","BEACH ROAD",150,"1.292781,103.853988",60,"150m","North East","North East","cycling","Continue Slightly Left Onto Beach Road"],["Right","BRAS BASAH ROAD",153,"1.293934,103.854685",55,"153m","South East","North East","cycling","Turn Right Onto Bras Basah Road"],["Straight","RAFFLES BOULEVARD",167,"1.293176,103.855823",60,"167m","South East","South East","cycling","Continue Onto Raffles Boulevard"],["Slight Left","TEMASEK BOULEVARD",86,"1.292395,103.857098",33,"86m","East","South East","cycling","Keep Left Onto Temasek Boulevard"],["Right","TEMASEK BOULEVARD",79,"1.292733,103.857679",76,"79m","East","North East","pushing bike","Turn Right To Stay On Temasek Boulevard"],["Right","TEMASEK BOULEVARD",129,"1.293241,103.858101",49,"129m","East","North East","cycling","Turn Right To Stay On Temasek Boulevard"],["Right","TEMASEK BOULEVARD",19,"1.293159,103.859254",7,"19m","South","East","cycling","Turn Right To Stay On Temasek Boulevard"],["Right","TEMASEK BOULEVARD",0,"1.293088,103.859354",0,"0m","North","East","cycling","You Have Arrived At Your Destination, On The Right"]],"route_name":["EU TONG SEN STREET","SAINT ANDREW'S ROAD"],"route_summary":{"end_point":"TEMASEK BOULEVARD","start_point":"SAGO STREET","total_distance":3071,"total_time":1270},"status":0,"status_message":"Found route between points"}],"route_geometry":"kiyFcbyxRf@gAJMaAe@b@}@Li@{A}@oAw@Ui@G]Qo@Uw@Wy@OM]UeAi@uAu@w@c@e@WQKcAi@^w@p@kApAuAPQr@e@fAe@dAe@b@k@BcBHaAMiBOs@S[k@m@u@Y{G_BcAc@mC{@oA]o@KSEaPcBkEi@_Ca@gBi@}CoA}@e@}BkAP]r@kAx@aBZs@F[A[IQKMq@[C[aBw@NeFJ?@S","route_instructions":[["Right","SAGO STREET",57,"1.281664,103.844335",32,"57m","South East","North","cycling","Head Southeast On Sago Street"],["Left","SOUTH BRIDGE ROAD",43,"1.281402,103.844772",43,"43m","North East","South East","pushing bike","Turn Left Onto South Bridge Road"],["Right","ANN SIANG HILL",65,"1.281729,103.844964",64,"65m","South East","North East","pushing bike","Turn Right Onto Ann Siang Hill"],["Left","CLUB STREET",268,"1.281483,103.845483",97,"268m","North East","East","cycling","Turn Left Onto Club Street"],["Straight","CHINA STREET",242,"1.282885,103.84731",91,"242m","North East","North East","cycling","Continue Onto China Street"],["Right","CHURCH STREET",324,"1.284717,103.848471",118,"324m","South East","North East","cycling","Turn Right Onto Church Street"],["Straight","CECIL STREET",94,"1.282656,103.850437",34,"94m","East","South East","cycling","Go Straight Onto Cecil Street"],["Slight Left","COLLYER QUAY",345,"1.282594,103.851271",124,"345m","East","East","cycling","Keep Left Onto Collyer Quay"],["Slight Right","FULLERTON ROAD",204,"1.284751,103.853043",74,"204m","North East","North","cycling","Keep Right Onto Fullerton Road"],["Straight","ESPLANADE DRIVE",572,"1.286439,103.853731",206,"572m","North","North","cycling","Continue Onto Esplanade Drive"],["Straight","NICOLL HIGHWAY",221,"1.291448,103.854847",84,"221m","North East","North","cycling","Continue Onto Nicoll Highway"],["Right","RAFFLES BOULEVARD",167,"1.293176,103.855823",60,"167m","South East","North East","cycling","Turn Right Onto Raffles Boulevard"],["Slight Left","TEMASEK BOULEVARD",86,"1.292395,103.857098",33,"86m","East","South East","cycling","Keep Left Onto Temasek Boulevard"],["Right","TEMASEK BOULEVARD",79,"1.292733,103.857679",76,"79m","East","North East","pushing bike","Turn Right To Stay On Temasek Boulevard"],["Right","TEMASEK BOULEVARD",129,"1.293241,103.858101",49,"129m","East","North East","cycling","Turn Right To Stay On Temasek Boulevard"],["Right","TEMASEK BOULEVARD",19,"1.293159,103.859254",7,"19m","South","East","cycling","Turn Right To Stay On Temasek Boulevard"],["Right","TEMASEK BOULEVARD",0,"1.293088,103.859354",0,"0m","North","East","cycling","You Have Arrived At Your Destination, On The Right"]],"route_name":["ESPLANADE DRIVE","TEMASEK BOULEVARD"],"route_summary":{"end_point":"TEMASEK BOULEVARD","start_point":"SAGO STREET","total_distance":2907,"total_time":1186},"status":0,"status_message":"Found route between points"},{"route_geometry":"yp{F}_|xR@I]A?RwAZu@NYFF^Rj@b@v@{BgAIRSN[J]?OCUKSQEYAUFWqBaAkAi@gAVC@ABe@~@S^ADAF?H@J@FDHNRc@A`B~AxC~BOXQM}AoAuAoAuAoAmBiBgAiAsA}AoBsCcCsDuAuB}AcCu@eAg@w@yAyBmCcEmB{CiLiS[JSBSCQAYCQCYMOG]OUKWQ[SYS[[Y_@OUUa@a@k@c@k@aAm@UCm@Cq@Ey@Eu@Lk@VYPKRGHiALk@FAEQ@i@CAYMgA@K@e@?]?O?SCUKg@IYG]EWM_@EQGU??SF??C?OFIBQDUFQD?@OBWHWHSFODQDGBA???MPMPJRPRJJVRHLFHHJJNDHLPHPNRHPLRiAx@GBIDEBA@EDOLEFGF_A~@IHGDEDCDEBKHCBGDMJEBCBEBEBEBC?C@IBE@EBG@A@C?MBI@KBo@HK@G@G@E@E?MBG@SkASDSBE@Jp@sBg@mAYu@Mg@A[G_@CUQg@g@OYuAn@BB@@FLHP@D@J?RENEHADEBGFMFu@d@WLOJc@Vu@d@OHQJ]TkBfA]RSLOHA@IBYHYHA?A?o@eA]NQFSHHXKP[Le@@S@W?OBU?O?S@K?K?M?M@I?K?O?G?E?u@B?dBE@Q?I?K?K?U@S?[?Q@I?[?U@M?W?K@O?AAW?K?Q@K?W?W@O?W?Q@Q?C?_DeBMGECGCIEGEGCQKKEOISIGCSIYIKICCUIE?OCKCSI[EG?e@Ec@G_@Cg@E[A_@Ai@C[CKIYQSMSBC?G@I?GDCFCFABIVMXKPCDABCFA@KJ??CFABOJAH???BKDIJCLCNEPEPCLCNCNERGVCTGXETI\\GXCNGTI`@Or@SHUCOR{A[ADCFAF?DCH?@ABCH?@ABCH?@ABA@?BA@ELA@ABADA@?@CFCDCFABABA@GLA@A@ABCFABEHEJEFEJGJGPGJe@~@GJFHe@pAO?SAeBk@WMi@Wi@UKGEACAIEe@So@GAAC?SCC?CAE?OCOACAOAEAE?EAQAEAEASAGAC?CAm@EYAaCH{CReDZ]DI@M@m@FMDE@E@M@E@I@GBC@KDG@C@G@[JIBG@IDCBC@CBCDCBEBSPEFC@IJa@`@GFKJGFCBEDEFC@?@CDEDAB]h@EDCD?BA@CBEBA@MTEHA@ADEByBjDeBvC_AvAs@fAU\\QZU^[d@EHOV]h@GJOTeAfBs@bAm@l@]\\c@Tm@J_AHC?Y@o@DQ?M?O?S?G?S?S?E?g@@a@Dw@Dy@Dg@Bi@DkADw@FuAJaAHcBL{@DcAFcBJqAHcAHo@D_AFSDa@Jm@X]R[P[R[P}@z@kAbAyAtAA@k@h@]X]ZSP]ZQPa@^QNWTIFGFGDk@ZKFWRIFEBSHUHcAj@{@d@}@f@e@Vi@Zk@Xc@V[PWZ[ZEFORQVCD_@b@KLILKLIFWZe@j@YZQRSRCBSROP?@A@IJEFIHKJILIHGHIHGHIHKJEFIJIJGFEDEDABGDEFKJGFIFGHIHGFKHIJKHIHGFKFGBGDMDKDIBMBMBI@IBK@KBI@C?E@EBEBCBCDEHEFEFGHEFCDKPEHGHEHCDCDCBADABADIl@AJAJCNAJCLAJCF?DCHCFEJEHEDEFEFCDGDIDGDEBGBKBG@IBG@IBI@IBE@G@GBIFGDC@EBEDEFCBABEFEHADCDADAFAFAH?BAF?H?B?B?B?B?B?@AB?@?B?BA@?B?@?BA@?B?@AB?BABA@ABABA@ABA@ABA@A@A@W\\IJIJOROPORILCBUXCAACCA}AmAECGEk@l@i@r@ABKZADAFAHAH?H?F?H?F@H?DG@C@I@E@G@G@EBE@EBEDC?A@A@EDEHCDEFCDABABMDKRABCFCDKPMDE@K?WAC?I@]GYGA^Ab@??KAMCICUIUICACAECCC?AA?AAA?CCA?C?C?A?AAA?CAEAGCCAC?CAA?AAGAKEGEKCMEQIG?ECGGCAIEGGIEGEIGIEECGEGC?A??A????A??A??A??A??A??????AAA??ACAAACCCAAAA??AA?A?AACAAACAA?CCCAAACACACCCACCAAEAACCACCCA??OKAAIEMK??iAs@YQCC_@UAAAA?AAAA?AAUK?AEAMGCAICSIC?C?A?A??AA?OEEAAAA?C?A?A?CAICOCGCA?MCKCMASESCGAMACGACACGA?C@Q@S@GDCBACGDC?C?A?C?ENiC@C?G??HMDO@WEO@YACHsAJcBBg@DK?G?Eg@?@WAa@","route_instructions":[["Right","TEMASEK BOULEVARD",33,"1.293088,103.859354",23,"33m","East","North","cycling","Head East On Temasek Boulevard"],["Right","TEMASEK BOULEVARD",98,"1.29323,103.859308",44,"98m","North","West","cycling","Turn Right To Stay On Temasek Boulevard"],["Left","TEMASEK AVENUE",83,"1.294072,103.85905",43,"83m","West","North","cycling","Turn Left Onto Temasek Avenue"],["Sharp Right","TEMASEK BOULEVARD",80,"1.293745,103.858389",82,"80m","North East","South West","pushing bike","Make A Sharp Right Onto Temasek Boulevard"],["Left","TEMASEK BOULEVARD",99,"1.294367,103.85875",37,"99m","North West","North East","cycling","Turn Left To Stay On Temasek Boulevard"],["Right","TEMASEK BOULEVARD",42,"1.295096,103.858677",22,"42m","East","North East","cycling","Turn Right To Stay On Temasek Boulevard"],["Left","TEMASEK BOULEVARD",122,"1.2951,103.859037",47,"122m","North East","East","cycling","Turn Left To Stay On Temasek Boulevard"],["Slight Left","UNNAMED ROAD",156,"1.296047,103.859583",66,"156m","North","North East","cycling","Make A Slight Left Onto Unnamed Road"],["Sharp Right","NICOLL HIGHWAY",21,"1.296618,103.85858",39,"21m","North","South West","pushing bike","Make A Sharp Right Onto Nicoll Highway"],["Sharp Left","NICOLL HIGHWAY",189,"1.296804,103.858588",72,"189m","South West","North","cycling","Make A Sharp Left To Stay On Nicoll Highway"],["Right","MIDDLE ROAD",17,"1.295538,103.857467",20,"17m","North West","South West","pushing bike","Turn Right Onto Middle Road"],["Right","NICOLL HIGHWAY",1668,"1.295619,103.857344",608,"1668m","North East","North West","cycling","Turn Right Onto Nicoll Highway"],["Left","Kallang Riverside Park",922,"1.304802,103.869118",340,"922m","North West","North East","cycling","Turn Left Onto Kallang Riverside Park"],["Left","Kallang Riverside Park",141,"1.31035,103.872638",52,"141m","North","East","cycling","Turn Left To Stay On Kallang Riverside Park"],["Slight Left","Kallang Riverside Park",187,"1.311522,103.872194",71,"187m","North West","North","cycling","Keep Left Onto Kallang Riverside Park"],["Right","Kallang Park Connector",397,"1.310791,103.870871",147,"397m","North West","South West","cycling","Continue Right Onto Kallang Park Connector"],["Slight Left","Kallang Park Connector",299,"1.31354,103.869657",116,"299m","West","North","cycling","Make A Slight Left To Stay On Kallang Park Connector"],["Left","Kallang Park Connector",56,"1.315643,103.870293",64,"56m","North West","North East","pushing bike","Turn Left To Stay On Kallang Park Connector"],["Left","Kallang Park Connector",410,"1.316073,103.870045",149,"410m","South West","North West","cycling","Continue Left Onto Kallang Park Connector"],["Right","Kallang Park Connector",48,"1.318586,103.867852",50,"48m","North East","North","pushing bike","Continue Right Onto Kallang Park Connector"],["Left","Kallang Park Connector",262,"1.318833,103.868198",103,"262m","North West","North East","cycling","Continue Left Onto Kallang Park Connector"],["Left","Whampoa Park Connector",58,"1.320894,103.867662",56,"58m","West","North","pushing bike","Turn Left Onto Whampoa Park Connector"],["Right","Whampoa Park Connector",18,"1.320893,103.867145",17,"18m","North","West","pushing bike","Turn Right To Stay On Whampoa Park Connector"],["Straight","Whampoa Park Connector",348,"1.321055,103.867142",125,"348m","North","North","cycling","Continue Straight Onto Whampoa Park Connector"],["Straight","Woodsville PC",767,"1.32403,103.867586",278,"767m","North East","North East","cycling","Continue Onto Woodsville Pc"],["Right","Kallang Park Connector",95,"1.328635,103.865719",94,"95m","North West","West","pushing bike","Turn Right Onto Kallang Park Connector"],["Left","Kallang Park Connector",2106,"1.329393,103.865729",758,"2106m","West","North","cycling","Turn Left To Stay On Kallang Park Connector"],["Slight Right","Kallang Park Connector",1758,"1.343455,103.85737",633,"1758m","North","North","cycling","Keep Right Onto Kallang Park Connector"],["Slight Right","Kallang Park Connector",33,"1.356872,103.850382",14,"33m","North West","North West","cycling","Keep Right Onto Kallang Park Connector"],["Slight Left","Bishan Ang Mo Kio Park",1226,"1.35707,103.850172",442,"1226m","West","North West","cycling","Continue Slightly Left Onto Bishan Ang Mo Kio Park"],["Slight Right","Ang Mo Kio Park Connector",692,"1.363825,103.843162",253,"692m","North West","North West","cycling","Continue Slightly Right Onto Ang Mo Kio Park Connector"],["Right","Ang Mo Kio",337,"1.368994,103.845289",131,"337m","East","North East","cycling","Turn Right To Stay On Ang Mo Kio"],["Left","ANG MO KIO AVENUE 3",22,"1.368592,103.848209",13,"22m","North","East","cycling","Turn Left Onto Ang Mo Kio Avenue 3"],["Right","ANG MO KIO AVENUE 3",33,"1.368786,103.848209",12,"33m","East","North","cycling","Turn Right To Stay On Ang Mo Kio Avenue 3"],["Left","ANG MO KIO AVENUE 3",0,"1.368794,103.848499",0,"0m","North","East","cycling","You Have Arrived At Your Destination, On The Left"]],"route_name":["NICOLL HIGHWAY","Kallang Park Connector"],"route_summary":{"end_point":"ANG MO KIO AVENUE 3","start_point":"TEMASEK BOULEVARD","total_distance":12805,"total_time":5007},"status":0,"status_message":"Found route between points"}],"user_exist_in_db":true},{"index":2,"Itinerary":[[1.2931,103.852],"Merlion Park","Sri Krishnan Temple","Fifth Season's Kolkata Beckons","Feng Food"],"POICategories":[["NA","NA","NA"],["nonfood","Parks","City Parks"],["nonfood","Place of Worship ","Indian Temple"],["food","NA","NA"],["food","NA","NA"]],"VehicleMode":"Cycle","Coords":[[1.2931,103.852],[1.2861885928,103.85415714],[1.3005147319,103.8526969186],[1.3082766366,103.8510258281],[1.4292441433,103.8361072314]],"StartTimePOI":[["Fri, 22 Sep 2023 10:00:00 GMT"],["Fri, 22 Sep 2023 11:07:42 GMT"],["Fri, 22 Sep 2023 12:20:18 GMT"],["Fri, 22 Sep 2023 13:28:32 GMT"]],"ReachTimePOI":[["Fri, 22 Sep 2023 10:07:42 GMT"],["Fri, 22 Sep 2023 11:20:18 GMT"],["Fri, 22 Sep 2023 12:28:32 GMT"],["Fri, 22 Sep 2023 15:22:45 GMT"]],"LeaveTimePOI":[["Fri, 22 Sep 2023 11:07:42 GMT"],["Fri, 22 Sep 2023 12:20:18 GMT"],["Fri, 22 Sep 2023 13:28:32 GMT"],["Fri, 22 Sep 2023 16:22:45 GMT"]],"TotalTime":"6h 22min","Total distance(km)":22.343,"Routes":[{"route_geometry":"qq{FypzxRh@VzAx@TJx@`@dAj@tExBFB`B~@lAaBd@m@V]r@{@Be@GU[Ut@@ZINIPS`@o@Ns@HY@IDGHAJ?PDRBR@r@GPM~ByCfAk@~AaAC?","route_instructions":[["Left","NORTH BRIDGE ROAD",393,"1.293213,103.851814",149,"393m","South West","North","cycling","Head Southwest On North Bridge Road"],["Left","PARLIAMENT PLACE",223,"1.290185,103.849996",92,"223m","South East","South West","cycling","Turn Left Onto Parliament Place"],["Sharp Right","CONNAUGHT DRIVE",57,"1.289392,103.851578",52,"57m","South","North East","pushing bike","Make A Sharp Right Onto Connaught Drive"],["Straight","CONNAUGHT DRIVE",48,"1.288903,103.851673",18,"48m","South East","South East","cycling","Continue Straight Onto Connaught Drive"],["Straight","CONNAUGHT DRIVE",103,"1.288639,103.852012",38,"103m","East","South East","cycling","Continue Straight To Stay On Connaught Drive"],["Straight","FULLERTON ROAD",264,"1.288066,103.852437",113,"264m","South","South","cycling","Go Straight Onto Fullerton Road"],["Sharp Left","ESPLANADE DRIVE",2,"1.286244,103.853866",2,"2m","North","South East","pushing bike","Make A Sharp Left Onto Esplanade Drive"],["Right","ESPLANADE DRIVE",0,"1.28626,103.85387",0,"0m","North","North","pushing bike","You Have Arrived At Your Destination, On The Right"]],"route_name":["NORTH BRIDGE ROAD","FULLERTON ROAD"],"route_summary":{"end_point":"ESPLANADE DRIVE","start_point":"NORTH BRIDGE ROAD","total_distance":1089,"total_time":462},"status":0,"status_message":"Found route between points"},{"alternativeroute":[{"route_geometry":"cfzFu}zxRq@K@RGLaPcBkEi@_Ca@gBi@EDg@l@{@p@uArA}@~Ag@dAk@`Ag@~@a@r@K\\}AnC{AnC{@bB]~@_CmAEIIIu@e@uC_CoAcAcCoB}@fAcAlAeEcDwAgAgA{@SO[`@","route_instructions":[["Right","ESPLANADE DRIVE",29,"1.28626,103.85387",39,"29m","North","North","pushing bike","Head North On Esplanade Drive"],["Left","ESPLANADE DRIVE",21,"1.286511,103.853932",11,"21m","West","North","cycling","Turn Left To Stay On Esplanade Drive"],["Right","ESPLANADE DRIVE",561,"1.286538,103.853759",207,"561m","North","North West","cycling","Turn Right To Stay On Esplanade Drive"],["Left","STAMFORD ROAD",690,"1.291448,103.854847",254,"690m","North West","North","cycling","Turn Left Onto Stamford Road"],["Right","STAMFORD ROAD",83,"1.294948,103.849774",30,"83m","North East","North West","cycling","Turn Right To Stay On Stamford Road"],["Slight Right","QUEEN STREET",316,"1.295586,103.850156",122,"316m","North East","North East","cycling","Keep Right Onto Queen Street"],["Left","WATERLOO LINK",111,"1.297746,103.851988",44,"111m","North West","North East","cycling","Turn Left Onto Waterloo Link"],["Right","WATERLOO STREET",273,"1.2984,103.851242",107,"273m","North East","North West","cycling","Turn Right Onto Waterloo Street"],["Left","BENCOOLEN LINK",25,"1.300292,103.852801",9,"25m","North West","North East","cycling","Turn Left Onto Bencoolen Link"],["Right","BENCOOLEN LINK",0,"1.300427,103.852628",0,"0m","North","North West","cycling","You Have Arrived At Your Destination, On The Right"]],"route_name":["ESPLANADE DRIVE","STAMFORD ROAD"],"route_summary":{"end_point":"BENCOOLEN LINK","start_point":"ESPLANADE DRIVE","total_distance":2106,"total_time":820},"status":0,"status_message":"Found route between points"}],"route_geometry":"cfzFu}zxRq@K@RGLaPcBkEi@_Ca@gBi@EDg@l@{@p@uArAO@S?MEWIwAu@_@Oo@[}@i@]AsBkAqCyAmBgAyAy@YQULSHOPUVUZyB~CqCnDWNGHwBvCGFEFsBdCIJgA{@SO[`@","route_instructions":[["Right","ESPLANADE DRIVE",29,"1.28626,103.85387",39,"29m","North","North","pushing bike","Head North On Esplanade Drive"],["Left","ESPLANADE DRIVE",21,"1.286511,103.853932",11,"21m","West","North","cycling","Turn Left To Stay On Esplanade Drive"],["Right","ESPLANADE DRIVE",561,"1.286538,103.853759",207,"561m","North","North West","cycling","Turn Right To Stay On Esplanade Drive"],["Left","STAMFORD ROAD",149,"1.291448,103.854847",55,"149m","North West","North","cycling","Turn Left Onto Stamford Road"],["Right","BEACH ROAD",194,"1.292406,103.853918",71,"194m","North","North West","cycling","Turn Right Onto Beach Road"],["Slight Left","BEACH ROAD",339,"1.293934,103.854685",126,"339m","North","North East","cycling","Make A Slight Left To Stay On Beach Road"],["Left","MIDDLE ROAD",567,"1.296516,103.856266",209,"567m","North West","North East","cycling","Turn Left Onto Middle Road"],["Right","WATERLOO STREET",67,"1.299827,103.852423",33,"67m","North East","North West","cycling","Turn Right Onto Waterloo Street"],["Left","BENCOOLEN LINK",25,"1.300292,103.852801",9,"25m","North West","North East","cycling","Turn Left Onto Bencoolen Link"],["Right","BENCOOLEN LINK",0,"1.300427,103.852628",0,"0m","North","North West","cycling","You Have Arrived At Your Destination, On The Right"]],"route_name":["ESPLANADE DRIVE","MIDDLE ROAD"],"route_summary":{"end_point":"BENCOOLEN LINK","start_point":"ESPLANADE DRIVE","total_distance":1948,"total_time":756},"status":0,"status_message":"Found route between points"},{"route_geometry":"u~|F}uzxRe@p@y@hA~AlAIJmBfCIJcAnAm@v@@J@LaAGqEAIAuAGq@G_@Ig@KWO[QiAq@kAi@g@a@w@a@qAq@QK{ApBqCvDQKkAu@}B{ACC","route_instructions":[["Right","BENCOOLEN LINK",87,"1.300427,103.852628",40,"87m","North West","North","cycling","Head Northwest On Bencoolen Link"],["Left","BENCOOLEN STREET",70,"1.30091,103.852013",30,"70m","South West","North West","cycling","Turn Left Onto Bencoolen Street"],["Right","MIDDLE ROAD",229,"1.300427,103.85162",88,"229m","North West","South West","cycling","Turn Right Onto Middle Road"],["Right","SELEGIE ROAD",362,"1.301632,103.850005",131,"362m","North","West","cycling","Turn Right Onto Selegie Road"],["Straight","SERANGOON ROAD",179,"1.304734,103.850682",72,"179m","North East","North East","cycling","Continue Onto Serangoon Road"],["Left","BUFFALO ROAD",213,"1.306087,103.851541",81,"213m","North West","North East","cycling","Turn Left Onto Buffalo Road"],["Right","RACE COURSE ROAD",154,"1.307284,103.850048",56,"154m","North East","North West","cycling","Turn Right Onto Race Course Road"],["Right","RACE COURSE ROAD",0,"1.308404,103.850858",0,"0m","North","North East","cycling","You Have Arrived At Your Destination, On The Right"]],"route_name":["MIDDLE ROAD","SELEGIE ROAD"],"route_summary":{"end_point":"RACE COURSE ROAD","start_point":"BENCOOLEN LINK","total_distance":1292,"total_time":494},"status":0,"status_message":"Found route between points"},{"route_geometry":"op~F{jzxRaCaBeGgE]UgAi@u@Uk@Q{@Wc@KYIv@w@b@]aAkAmAoA}A}Aa@RwA{A}A}A_@c@aAiAcAmASUqAoAnBiBmHkFyCyBmBwAeE}CuC}B}EiDiBqAg@_@}BcBy@k@YUo@c@WS{@o@aGkEcBqAmA{@g@]eDiCQNrBvAg@l@WReAz@q@\\A@qAy@EEY?kBsASMEC]b@SVGHMPi@t@q@e@QI_@QSHUCOR{A[ADCFAF?DCH?@ABCH?@ABCH?@ABA@?BA@ELA@ABADA@?@CFCDCFABABA@GLA@A@ABCFABEHEJEFEJGJGPGJe@~@GJFHe@pAO?SAeBk@WMi@Wi@UKGEACAIEe@So@GAAC?SCC?CAE?OCOACAOAEAE?EAQAEAEASAGAC?CAm@EYAaCH{CReDZ]DI@M@m@FMDE@E@M@E@I@GBC@KDG@C@G@[JIBG@IDCBC@CBCDCBEBSPEFC@IJa@`@GFKJGFCBEDEFC@?@CDEDAB]h@EDCD?BA@CBEBA@MTEHA@ADEByBjDeBvC_AvAs@fAU\\QZU^[d@EHOV]h@GJOTeAfBs@bAm@l@]\\c@Tm@J_AHC?Y@o@DQ?M?O?S?G?S?S?E?g@@a@Dw@Dy@Dg@Bi@DkADw@FuAJaAHcBL{@DcAFcBJqAHcAHo@D_AFSDa@Jm@X]R[P[R[P}@z@kAbAyAtAA@k@h@]X]ZSP]ZQPa@^QNWTIFGFGDk@ZKFWRIFEBSHUHcAj@{@d@}@f@e@Vi@Zk@Xc@V[PWZ[ZEFORQVCD_@b@KLILKLIFWZe@j@YZQRSRCBSROP?@A@IJEFIHKJILIHGHIHGHIHKJEFIJIJGFEDEDABGDEFKJGFIFGHIHGFKHIJKHIHGFKFGBGDMDKDIBMBMBI@IBK@KBI@C?E@EBEBCBCDEHEFEFGHEFCDKPEHGHEHCDCDCBADABADIl@AJAJCNAJCLAJCF?DCHCFEJEHEDEFEFCDGDIDGDEBGBKBG@IBG@IBI@IBE@G@GBIFGDC@EBEDEFCBABEFEHADCDADAFAFAH?BAF?H?B?B?B?B?B?@AB?@?B?BA@?B?@?BA@?B?@AB?BABA@ABABA@ABA@ABA@A@A@W\\IJIJOROPORILCBUXCAACCA}AmAECGEk@l@i@r@ABKZADAFAHAH?H?F?H?F@H?DG@C@I@E@G@G@EBE@EBEDC?A@A@EDEHCDEFCDABABMDKRABCFCDKPMDE@K?WAC?I@]GYGA^Ab@??KAMCICUIUICACAECCC?AA?AAA?CCA?C?C?A?AAA?CAEAGCCAC?CAA?AAGAKEGEKCMEQIG?ECGGCAIEGGIEGEIGIEECGEGC?A??A????A??A??A??A??A??????AAA??ACAAACCCAAAA??AA?A?AACAAACAA?CCCAAACACACCCACCAAEAACCACCCA??OKAAIEMK??iAs@YQCC_@UAAAA?AAAA?AAUK?AEAMGCAICSIC?C?A?A??AA?OEEAAAA?C?A?A?CAICOCGCA?MCKCMASESCGAMACGACACGAUCG?QJCBA@KCA?CA_@C]ACAA???A@A?EBE@E?G@??GAEAEAAAA??AAAA?AA??A?AAA@A?A?A@A?A@A@A?G?IAA?E?E?I?A?A?A@A?A?A?A???A??AA?AAA?MAAAA@C???A?A?A?A@E???C?C?AAC?A?A???A?C?I?G@A???CAC?A?A???A?A?C@C@A?K@M?K@Q@O@M@K@Q@C?EBMCIAE?O@EPG@C?G@C@mCf@q@NI@sAVmATwAXUBC@AC]?S?G?E?I?G@k@RI@I@K?G?IAIAKCKCMCMAA?I?KAK@M?wAAeD?Q?@}@?Wc@??@CZW@{@FkIf@cAHgBJcAJWB_@FeBTaBDc@@o@@gBDcCJoBf@oK|CgA\\o@`@s@`Am@`Ai@b@g@Vc@L]JwAd@{Bn@yAt@k@\\qAbAyA~AuElI{@~AcEpHyAlCaAhBo@hAGLgCtEw@vAkC~EqC|EcEzE{BfB?@e@VcB~@a@RA@aGtBoDz@uIt@AAASAMAKAGAIqGKQAQ?o@IkEcAyAi@u@S[Gq@O[GoKiCUKUIYUs@[w@Yc@OOJIHAf@GCOEMGBDH@AN?BYKQHA@IBC@EGIIGEKIMGQEKCE?C@C@C@C@E?C?CAMGGCECEGEEGGGEMEGCYMw@i@kAe@WKy@a@CAC?EAG?MAGCe@U]OAACCCCEEACAAAACAC?A?A?A?E?C?C?CAm@WaAa@kAc@kBu@a@Ug@Sk@UMEGA]KCAw@Ya@MICCAGEGEUKKEICE?CAC?]B]MEAQ?CBABADADCBE?GAcDqAc@S[MXq@NKBIWKCAWKGBE@C?M?OCOEUIUKUKSKSKSMs@[K?IAGCKEICKGKEKCMEKCMCKCKCGAEACAECCECAECEA[Ea@G_@EQAK?E?E?C@M@M@q@CoACcBCEAI?E@G??ANK\\O}@EC?UABHCH?FCAS@IF??CBKHM?ANAFGBG@{AEKAMEMCIC]YEAgEIO?MBKDG?OGCEQAAJy@AOCKI[AKDIBI?OAI@O?SA]AKAOCMAqDEO?G@IBI@_@AY?MHMFWTOLSBgACW?sDE?S@Q@_@FMIMY???U?GJCB??DI?G?Y@g@@U?I?g@BkA@o@?a@@UH?N??UhCB?TCpBx@BAR","route_instructions":[["Right","RACE COURSE ROAD",472,"1.308404,103.850858",177,"472m","North East","North","cycling","Head Northeast On Race Course Road"],["Right","BIRCH ROAD",71,"1.311968,103.853097",34,"71m","South East","North","cycling","Turn Right Onto Birch Road"],["Left","FARRER PARK STATION ROAD",193,"1.311508,103.853528",76,"193m","North East","South East","cycling","Turn Left Onto Farrer Park Station Road"],["Left","RANGOON ROAD",22,"1.312703,103.85478",11,"22m","North West","North East","cycling","Turn Left Onto Rangoon Road"],["Right","RACE COURSE ROAD",366,"1.312866,103.854676",136,"366m","North East","North West","cycling","Turn Right Onto Race Course Road"],["Right","UNNAMED ROAD",86,"1.315122,103.857062",41,"86m","South East","North East","cycling","Turn Right Onto Unnamed Road"],["Left","SERANGOON ROAD",1609,"1.314562,103.857586",586,"1609m","North East","South East","cycling","Turn Left Onto Serangoon Road"],["Left","Kallang Park Connector",14,"1.32589,103.866577",24,"14m","North West","North East","pushing bike","Turn Left Onto Kallang Park Connector"],["Left","Kallang Park Connector",218,"1.325984,103.866497",81,"218m","South West","North West","cycling","Continue Left Onto Kallang Park Connector"],["Right","Kallang Park Connector",57,"1.326327,103.865269",51,"57m","North East","North West","pushing bike","Continue Right Onto Kallang Park Connector"],["Straight","Kallang Park Connector",279,"1.326738,103.865561",111,"279m","North East","North East","cycling","Continue Straight Onto Kallang Park Connector"],["Left","Kallang Park Connector",95,"1.328635,103.865719",94,"95m","North West","North East","pushing bike","Turn Left Onto Kallang Park Connector"],["Left","Kallang Park Connector",2106,"1.329393,103.865729",758,"2106m","West","North","cycling","Turn Left To Stay On Kallang Park Connector"],["Slight Right","Kallang Park Connector",1758,"1.343455,103.85737",633,"1758m","North","North","cycling","Keep Right Onto Kallang Park Connector"],["Slight Right","Kallang Park Connector",33,"1.356872,103.850382",14,"33m","North West","North West","cycling","Keep Right Onto Kallang Park Connector"],["Slight Left","Bishan Ang Mo Kio Park",1226,"1.35707,103.850172",442,"1226m","West","North West","cycling","Continue Slightly Left Onto Bishan Ang Mo Kio Park"],["Slight Right","Ang Mo Kio Park Connector",1007,"1.363825,103.843162",366,"1007m","North West","North West","cycling","Continue Slightly Right Onto Ang Mo Kio Park Connector"],["Slight Left","Ang Mo Kio Town Garden West",697,"1.371715,103.84523",264,"697m","North","North","cycling","Make A Slight Left Onto Ang Mo Kio Town Garden West"],["Left","ANG MO KIO AVENUE 5",16,"1.377319,103.844835",9,"16m","West","North","cycling","Turn Left Onto Ang Mo Kio Avenue 5"],["Right","ANG MO KIO AVENUE 6",1242,"1.377341,103.844693",447,"1242m","North","West","cycling","Turn Right Onto Ang Mo Kio Avenue 6"],["Straight","LENTOR AVENUE",2389,"1.387735,103.84162",865,"2389m","North West","North West","cycling","Continue Onto Lentor Avenue"],["Right","Lower Seletar Res Park 1",918,"1.402633,103.827446",348,"918m","East","North","cycling","Turn Right Onto Lower Seletar Res Park 1"],["Right","YISHUN AVENUE 2",23,"1.409964,103.829658",32,"23m","North East","West","cycling","Turn Right Onto Yishun Avenue 2"],["Sharp Left","YISHUN AVENUE 2",10,"1.410149,103.829749",17,"10m","South West","North East","pushing bike","Make A Sharp Left To Stay On Yishun Avenue 2"],["Right","YISHUN AVENUE 1",12,"1.410076,103.829714",10,"12m","West","South","cycling","Turn Right Onto Yishun Avenue 1"],["Right","Khatib Bongsu Park Connector",497,"1.410089,103.829611",182,"497m","North East","West","cycling","Turn Right Onto Khatib Bongsu Park Connector"],["Slight Right","Khatib Bongsu Park Connector",1139,"1.413954,103.831445",421,"1139m","North East","North East","cycling","Keep Right Onto Khatib Bongsu Park Connector"],["Sharp Right","YISHUN AVENUE 2",31,"1.422693,103.834827",50,"31m","South East","North","pushing bike","Make A Sharp Right Onto Yishun Avenue 2"],["Sharp Left","YISHUN AVENUE 2",49,"1.422464,103.834973",34,"49m","North","South East","cycling","Make A Sharp Left To Stay On Yishun Avenue 2"],["Left","YISHUN AVENUE 3",17,"1.422901,103.835006",12,"17m","South West","North","cycling","Turn Left Onto Yishun Avenue 3"],["Right","Yishun Park Connector",967,"1.422903,103.834873",362,"967m","North","West","cycling","Turn Right Onto Yishun Park Connector"],["Sharp Right","Yishun",11,"1.430574,103.83515",5,"11m","East","North West","cycling","Make A Sharp Right To Stay On Yishun"],["Slight Left","Yishun",177,"1.430542,103.835241",68,"177m","East","East","cycling","Keep Left Onto Yishun"],["Right","Yishun",15,"1.430484,103.836832",14,"15m","South","East","cycling","Turn Right To Stay On Yishun"],["Left","YISHUN CENTRAL",13,"1.43035,103.836829",9,"13m","East","South","cycling","Turn Left Onto Yishun Central"],["Right","YISHUN CENTRAL 1",77,"1.430346,103.83694",32,"77m","South","East","cycling","Turn Right To Stay On Yishun Central 1"],["Right","YISHUN CENTRAL SERVICE ROAD",76,"1.429657,103.836916",36,"76m","West","South","cycling","Turn Right Onto Yishun Central Service Road"],["Left","YISHUN CENTRAL SERVICE ROAD",43,"1.429676,103.836236",16,"43m","South","West","cycling","Turn Left To Stay On Yishun Central Service Road"],["Left","YISHUN CENTRAL SERVICE ROAD",0,"1.429401,103.83612",0,"0m","North","West","cycling","You Have Arrived At Your Destination, On The Left"]],"route_name":["Kallang Park Connector","LENTOR AVENUE"],"route_summary":{"end_point":"YISHUN CENTRAL SERVICE ROAD","start_point":"RACE COURSE ROAD","total_distance":18014,"total_time":6853},"status":0,"status_message":"Found route between points"}],"user_exist_in_db":true}]